lightml/__init__.py
lightml/model.py
lightml-0.0.4.dist-info/LICENSE
lightml-0.0.4.dist-info/METADATA
lightml-0.0.4.dist-info/WHEEL
lightml-0.0.4.dist-info/top_level.txt
lightml-0.0.4.dist-info/RECORD
